{
  "sa_iterations": 30,
  "recorded": 30,
  "terminated_early": false,
  "termination_reason": "",
  "iterations": [
    {"index": 1, "total": 30, "move": "module-rotate", "changed": true, "accept": false, "next_cost": 12800002.467465613, "current_cost": 2400002.2000000002, "best_cost": 2400002.2000000002, "temperature": 5},
    {"index": 2, "total": 30, "move": "module-swap", "changed": true, "accept": false, "next_cost": 5900003.4251380535, "current_cost": 2400002.2000000002, "best_cost": 2400002.2000000002, "temperature": 4.7999999999999998},
    {"index": 3, "total": 30, "move": "module-delete-insert", "changed": true, "accept": false, "next_cost": 14900002.445947731, "current_cost": 2400002.2000000002, "best_cost": 2400002.2000000002, "temperature": 4.6079999999999997},
    {"index": 4, "total": 30, "move": "module-rotate", "changed": true, "accept": false, "next_cost": 14500002.510020897, "current_cost": 2400002.2000000002, "best_cost": 2400002.2000000002, "temperature": 4.4236799999999992},
    {"index": 5, "total": 30, "move": "lcp-delete-insert", "changed": true, "accept": false, "next_cost": 14900002.445947731, "current_cost": 2400002.2000000002, "best_cost": 2400002.2000000002, "temperature": 4.2467327999999993},
    {"index": 6, "total": 30, "move": "lcp-delete-insert", "changed": true, "accept": false, "next_cost": 15900002.420027915, "current_cost": 2400002.2000000002, "best_cost": 2400002.2000000002, "temperature": 4.076863487999999},
    {"index": 7, "total": 30, "move": "module-swap", "changed": true, "accept": false, "next_cost": 3600003.13394628, "current_cost": 2400002.2000000002, "best_cost": 2400002.2000000002, "temperature": 3.9137889484799988},
    {"index": 8, "total": 30, "move": "module-rotate", "changed": true, "accept": false, "next_cost": 3600002.5229365402, "current_cost": 2400002.2000000002, "best_cost": 2400002.2000000002, "temperature": 3.7572373905407987},
    {"index": 9, "total": 30, "move": "module-swap", "changed": true, "accept": false, "next_cost": 2500002.6695576254, "current_cost": 2400002.2000000002, "best_cost": 2400002.2000000002, "temperature": 3.6069478949191667},
    {"index": 10, "total": 30, "move": "lcp-swap", "changed": true, "accept": false, "next_cost": 14900002.445947731, "current_cost": 2400002.2000000002, "best_cost": 2400002.2000000002, "temperature": 3.4626699791224},
    {"index": 11, "total": 30, "move": "module-swap", "changed": true, "accept": true, "next_cost": 1200003.0537073319, "current_cost": 1200003.0537073319, "best_cost": 1200003.0537073319, "temperature": 3.324163179957504},
    {"index": 12, "total": 30, "move": "module-rotate", "changed": true, "accept": true, "next_cost": 1200003.363887056, "current_cost": 1200003.363887056, "best_cost": 1200003.0537073319, "temperature": 3.1911966527592037},
    {"index": 13, "total": 30, "move": "lcp-delete-insert", "changed": true, "accept": true, "next_cost": 630109.55675798759, "current_cost": 630109.55675798759, "best_cost": 630109.55675798759, "temperature": 3.0635487866488353},
    {"index": 14, "total": 30, "move": "module-rotate", "changed": true, "accept": false, "next_cost": 730109.62686539732, "current_cost": 630109.55675798759, "best_cost": 630109.55675798759, "temperature": 2.9410068351828818},
    {"index": 15, "total": 30, "move": "module-rotate", "changed": true, "accept": false, "next_cost": 1200003.856519812, "current_cost": 630109.55675798759, "best_cost": 630109.55675798759, "temperature": 2.8233665617755666},
    {"index": 16, "total": 30, "move": "module-delete-insert", "changed": true, "accept": false, "next_cost": 9000003.2966061179, "current_cost": 630109.55675798759, "best_cost": 630109.55675798759, "temperature": 2.710431899304544},
    {"index": 17, "total": 30, "move": "lcp-delete-insert", "changed": true, "accept": false, "next_cost": 1400004.1594258046, "current_cost": 630109.55675798759, "best_cost": 630109.55675798759, "temperature": 2.6020146233323622},
    {"index": 18, "total": 30, "move": "lcp-delete-insert", "changed": true, "accept": false, "next_cost": 700019.95398139174, "current_cost": 630109.55675798759, "best_cost": 630109.55675798759, "temperature": 2.4979340383990678},
    {"index": 19, "total": 30, "move": "module-delete-insert", "changed": true, "accept": false, "next_cost": 1400004.6862581403, "current_cost": 630109.55675798759, "best_cost": 630109.55675798759, "temperature": 2.3980166768631048},
    {"index": 20, "total": 30, "move": "module-swap", "changed": true, "accept": false, "next_cost": 4700004.0819783686, "current_cost": 630109.55675798759, "best_cost": 630109.55675798759, "temperature": 2.3020960097885808},
    {"index": 21, "total": 30, "move": "module-delete-insert", "changed": true, "accept": false, "next_cost": 1200004.7124244634, "current_cost": 630109.55675798759, "best_cost": 630109.55675798759, "temperature": 2.2100121693970376},
    {"index": 22, "total": 30, "move": "module-swap", "changed": true, "accept": false, "next_cost": 4700004.0819783686, "current_cost": 630109.55675798759, "best_cost": 630109.55675798759, "temperature": 2.1216116826211562},
    {"index": 23, "total": 30, "move": "lcp-delete-insert", "changed": true, "accept": true, "next_cost": 600005.47207642649, "current_cost": 600005.47207642649, "best_cost": 600005.47207642649, "temperature": 2.0367472153163098},
    {"index": 24, "total": 30, "move": "module-swap", "changed": true, "accept": false, "next_cost": 2900004.5562556949, "current_cost": 600005.47207642649, "best_cost": 600005.47207642649, "temperature": 1.9552773267036574},
    {"index": 25, "total": 30, "move": "lcp-swap", "changed": true, "accept": false, "next_cost": 2400004.1263946928, "current_cost": 600005.47207642649, "best_cost": 600005.47207642649, "temperature": 1.8770662336355111},
    {"index": 26, "total": 30, "move": "module-swap", "changed": true, "accept": false, "next_cost": 1300003.0550448168, "current_cost": 600005.47207642649, "best_cost": 600005.47207642649, "temperature": 1.8019835842900906},
    {"index": 27, "total": 30, "move": "module-rotate", "changed": true, "accept": false, "next_cost": 1300003.5400524228, "current_cost": 600005.47207642649, "best_cost": 600005.47207642649, "temperature": 1.729904240918487},
    {"index": 28, "total": 30, "move": "lcp-swap", "changed": true, "accept": false, "next_cost": 2400004.1263946928, "current_cost": 600005.47207642649, "best_cost": 600005.47207642649, "temperature": 1.6607080712817475},
    {"index": 29, "total": 30, "move": "lcp-swap", "changed": true, "accept": false, "next_cost": 2400004.1263946928, "current_cost": 600005.47207642649, "best_cost": 600005.47207642649, "temperature": 1.5942797484304776},
    {"index": 30, "total": 30, "move": "module-rotate", "changed": true, "accept": false, "next_cost": 1300003.8449380109, "current_cost": 600005.47207642649, "best_cost": 600005.47207642649, "temperature": 1.5305085584932585}
  ]
}
